<?xml version="1.0" encoding="UTF-8"?>
<?xml-stylesheet type="text/xsl" href="../src/07.xsl"?>
<network>
    <ethernets>
        <name>enp0s3</name>
        <addresses>192.168.10.10/24</addresses>
    </ethernets>
    <ethernets>
        <name>enp0s8</name>
        <addresses>192.168.20.10/24</addresses>
    </ethernets>
    <ethernets>
        <name>enp0s9</name>
        <addresses>192.168.30.10/24</addresses>
        <gateway4>192.168.30.1</gateway4>
        <nameservers>
            <addresses>8.8.8.8</addresses>
            <addresses>8.8.4.4</addresses>
        </nameservers>
    </ethernets>
</network>
